nalibsSkyJoy/__base.py
nalibsSkyJoy/__init__.py
nalibsSkyJoy/__version.py
nalibsSkyJoy/main.py
nalibs_skyjoy-0.3.1.dist-info/LICENSE
nalibs_skyjoy-0.3.1.dist-info/METADATA
nalibs_skyjoy-0.3.1.dist-info/WHEEL
nalibs_skyjoy-0.3.1.dist-info/entry_points.txt
nalibs_skyjoy-0.3.1.dist-info/top_level.txt
nalibs_skyjoy-0.3.1.dist-info/RECORD
