Metadata-Version: 2.1
Name: nalibs-skyjoy
Version: 0.3.1
Summary: qana - tiny package - nalibsSkyJoy
Author-email: Ron <naq0310@gmail.com>
Maintainer-email: Ron <naq0310@gmail.com>
Project-URL: Homepage, https://github.com/pypa/sampleproject
Project-URL: Issues, https://github.com/pypa/sampleproject/issues
Classifier: Programming Language :: Python :: 3
Classifier: License :: OSI Approved :: MIT License
Classifier: Operating System :: OS Independent
Requires-Python: >=3.9
License-File: LICENSE
Requires-Dist: nalibs-utility ==1.0.0
Requires-Dist: nalibs-aws ==0.3.0
